Core/__init__.py
Core/imagehawk.py
Core/Engines/__init__.py
Core/Engines/image_embeddings.py
Core/Engines/text_embeddings.py
Core/VectorStores/__init__.py
Core/VectorStores/qdrantvectorstore.py
imagehawk-1.0.1.dist-info/METADATA
imagehawk-1.0.1.dist-info/WHEEL
imagehawk-1.0.1.dist-info/top_level.txt
imagehawk-1.0.1.dist-info/RECORD
