Metadata-Version: 2.1
Name: imagehawk
Version: 1.0.1
Summary: A package for text to image search using embeddings
Home-page: 
Author: Junaid Bashir
Author-email: 
Classifier: Programming Language :: Python :: 3
Classifier: License :: OSI Approved :: MIT License
Classifier: Operating System :: OS Independent
Requires-Dist: qdrant-client==1.11.1
Requires-Dist: transformers==4.44.2
Requires-Dist: requests==2.32.3
Requires-Dist: torch==2.4.1
